{"is_source_file": true, "format": "JavaScript", "description": "This file contains API functions for managing coupons in the e-commerce front-end, including operations to list, get, create, update, and delete coupons.", "external_files": ["./client"], "external_methods": ["get", "post", "put", "del"], "published": ["listCoupons", "getCoupon", "createCoupon", "updateCoupon", "deleteCoupon"], "classes": [], "methods": [{"name": "listCoupons", "description": "Fetches a list of coupons with optional query parameters."}, {"name": "getCoupon", "description": "Retrieves details of a specific coupon by its ID."}, {"name": "createCoupon", "description": "Creates a new coupon with the given data."}, {"name": "updateCoupon", "description": "Updates an existing coupon by its ID with new data."}, {"name": "deleteCoupon", "description": "Deletes a coupon specified by its ID."}], "calls": ["get", "post", "put", "del"], "search-terms": ["couponsApi", "API", "coupons", "manageCoupons", "ecommerce_frontend"], "state": 2, "file_id": 22, "knowledge_revision": 51, "git_revision": "", "ctags": [{"_type": "tag", "name": "createCoupon", "path": "/home/kavia/workspace/code-generation/modern-e-commerce-platform-220291-220280/ecommerce_frontend/src/api/couponsApi.js", "pattern": "/^export const createCoupon = (data) => post(\"\\/coupons\", data);$/", "language": "JavaScript", "kind": "constant"}, {"_type": "tag", "name": "deleteCoupon", "path": "/home/kavia/workspace/code-generation/modern-e-commerce-platform-220291-220280/ecommerce_frontend/src/api/couponsApi.js", "pattern": "/^export const deleteCoupon = (id) => del(`\\/coupons\\/${id}`);$/", "language": "JavaScript", "kind": "constant"}, {"_type": "tag", "name": "getCoupon", "path": "/home/kavia/workspace/code-generation/modern-e-commerce-platform-220291-220280/ecommerce_frontend/src/api/couponsApi.js", "pattern": "/^export const getCoupon = (id) => get(`\\/coupons\\/${id}`);$/", "language": "JavaScript", "kind": "constant"}, {"_type": "tag", "name": "listCoupons", "path": "/home/kavia/workspace/code-generation/modern-e-commerce-platform-220291-220280/ecommerce_frontend/src/api/couponsApi.js", "pattern": "/^export const listCoupons = (params) => get(\"\\/coupons\", { params });$/", "language": "JavaScript", "kind": "constant"}, {"_type": "tag", "name": "updateCoupon", "path": "/home/kavia/workspace/code-generation/modern-e-commerce-platform-220291-220280/ecommerce_frontend/src/api/couponsApi.js", "pattern": "/^export const updateCoupon = (id, data) => put(`\\/coupons\\/${id}`, data);$/", "language": "JavaScript", "kind": "constant"}], "hash": "bcfbdaaaa67aa74f1be3c0b8e4464c27", "format-version": 4, "code-base-name": "ecommerce_frontend", "filename": "ecommerce_frontend/src/api/couponsApi.js", "revision_history": [{"51": ""}]}